commit_maker/__init__.py
commit_maker/main.py
commit_maker-0.2.2.dist-info/licenses/LICENSE
commit_maker-0.2.2.dist-info/METADATA
commit_maker-0.2.2.dist-info/WHEEL
commit_maker-0.2.2.dist-info/entry_points.txt
commit_maker-0.2.2.dist-info/top_level.txt
commit_maker-0.2.2.dist-info/RECORD
