Metadata-Version: 2.4
Name: commit-maker
Version: 0.2.2
Summary: CLI-утилита для генерации git-коммитов с помощью ИИ
Author-email: Alex Bulgakov <sashayerty@ya.ru>
License: MIT
Project-URL: Homepage, https://github.com/sashayerty/commit_maker
Requires-Python: >=3.8
License-File: LICENSE
Requires-Dist: requests>=2.32.3
Requires-Dist: rich-argparse>=1.7.0
Dynamic: license-file
